dope3/__init__.py
dope3/dope.py
dope3-3.1.0.dist-info/LICENSE
dope3-3.1.0.dist-info/WHEEL
dope3-3.1.0.dist-info/METADATA
dope3-3.1.0.dist-info/RECORD
